torfcli/__init__.py
torfcli/__main__.py
torfcli/_config.py
torfcli/_errors.py
torfcli/_main.py
torfcli/_term.py
torfcli/_ui.py
torfcli/_utils.py
torfcli/_vars.py
torf_cli-5.2.1.dist-info/LICENSE
torf_cli-5.2.1.dist-info/METADATA
torf_cli-5.2.1.dist-info/WHEEL
torf_cli-5.2.1.dist-info/entry_points.txt
torf_cli-5.2.1.dist-info/top_level.txt
torf_cli-5.2.1.dist-info/RECORD
