Metadata-Version: 2.1
Name: torf-cli
Version: 5.2.1
Summary: CLI tool to create, read and edit torrent files
Author-email: Random User <rndusr@posteo.de>
License: GPL-3.0-or-later
Project-URL: Repository, https://github.com/rndusr/torf-cli
Project-URL: Documentation, https://rndusr.github.io/torf-cli/torf.1.html
Project-URL: Bug Tracker, https://github.com/rndusr/torf-cli/issues
Project-URL: Changelog, https://raw.githubusercontent.com/rndusr/torf-cli/master/CHANGELOG
Keywords: bittorrent,torrent,magnet,cli
Classifier: Development Status :: 5 - Production/Stable
Classifier: Intended Audience :: End Users/Desktop
Classifier: License :: OSI Approved :: GNU General Public License v3 or later (GPLv3+)
Classifier: Programming Language :: Python :: 3
Requires-Python: >=3.7
License-File: LICENSE
Requires-Dist: torf ==4.*,>=4.1.2
Requires-Dist: pyxdg
Provides-Extra: dev
Requires-Dist: pytest ; extra == 'dev'
Requires-Dist: tox ; extra == 'dev'
Requires-Dist: coverage ; extra == 'dev'
Requires-Dist: pytest-cov ; extra == 'dev'
Requires-Dist: ruff ; extra == 'dev'
Requires-Dist: flake8 ; extra == 'dev'
Requires-Dist: isort ; extra == 'dev'
